datasubclasses/__init__.py
datasubclasses/tests/__init__.py
datasubclasses/tests/test_1984.py
datasubclasses/tests/test_subclassing.py
datasubclasses-0.0.1.dev0.dist-info/LICENSE.txt
datasubclasses-0.0.1.dev0.dist-info/METADATA
datasubclasses-0.0.1.dev0.dist-info/WHEEL
datasubclasses-0.0.1.dev0.dist-info/top_level.txt
datasubclasses-0.0.1.dev0.dist-info/RECORD
