Metadata-Version: 2.1
Name: datasubclasses
Version: 0.0.1.dev0
Summary: datasubclasses
Author-email: Johannes <johannes-programming@mailfence.com>
License: The MIT License (MIT)
Project-URL: Documentation, https://pypi.org/project/datasubclasses
Project-URL: Download, https://pypi.org/project/datasubclasses/#files
Project-URL: Source, https://github.com/johannes-programming/datasubclasses
Classifier: Development Status :: 2 - Pre-Alpha
Classifier: License :: OSI Approved :: MIT License
Classifier: Programming Language :: Python
Classifier: Programming Language :: Python :: 3
Classifier: Programming Language :: Python :: 3 :: Only
Requires-Python: >=3.12.5
License-File: LICENSE.txt
